bulldozer/__init__.py
bulldozer/_version.py
bulldozer/extraction/__init__.py
bulldozer/extraction/drape_cloth.py
bulldozer/multiprocessing/__init__.py
bulldozer/multiprocessing/bulldozer_executor.py
bulldozer/multiprocessing/bulldozer_manager.py
bulldozer/multiprocessing/utils.py
bulldozer/pipeline/__init__.py
bulldozer/pipeline/bulldozer_parameters.py
bulldozer/pipeline/bulldozer_pipeline.py
bulldozer/postprocessing/__init__.py
bulldozer/postprocessing/fill_pits.py
bulldozer/preprocessing/__init__.py
bulldozer/preprocessing/border.cp310-win_amd64.pyd
bulldozer/preprocessing/fill.cp310-win_amd64.pyd
bulldozer/preprocessing/regular.cp310-win_amd64.pyd
bulldozer/preprocessing/border_detection/__init__.py
bulldozer/preprocessing/border_detection/border_detector.py
bulldozer/preprocessing/dsm_filling/__init__.py
bulldozer/preprocessing/dsm_filling/dsm_filler.py
bulldozer/preprocessing/ground_detection/__init__.py
bulldozer/preprocessing/ground_detection/ground_anchors_detector.py
bulldozer/preprocessing/regular_detection/__init__.py
bulldozer/preprocessing/regular_detection/regular_detector.py
bulldozer/scale/__init__.py
bulldozer/utils/__init__.py
bulldozer/utils/bulldozer_argparse.py
bulldozer/utils/bulldozer_logger.py
bulldozer/utils/config_parser.py
bulldozer/utils/helper.py
bulldozer_dtm-1.2.0.dist-info/licenses/LICENSE
bulldozer_dtm-1.2.0.dist-info/METADATA
bulldozer_dtm-1.2.0.dist-info/WHEEL
bulldozer_dtm-1.2.0.dist-info/entry_points.txt
bulldozer_dtm-1.2.0.dist-info/top_level.txt
bulldozer_dtm-1.2.0.dist-info/RECORD
