Metadata-Version: 2.4
Name: bulldozer-dtm
Version: 1.2.0
Summary: Bulldozer is a DTM extraction tool requiring only a DSM as input
Home-page: https://github.com/CNES/bulldozer
Author: CNES
Author-email: dimitri.lallement@cnes.fr
License: Apache V2.0
Keywords: bulldozer,DTM,DSM,3D,Photogrammetry,Remote Sensing,LiDAR,CARS
Classifier: Development Status :: 4 - Beta
Classifier: Intended Audience :: Developers
Classifier: Intended Audience :: End Users/Desktop
Classifier: Intended Audience :: Science/Research
Classifier: Topic :: Software Development :: Libraries :: Python Modules
Classifier: License :: OSI Approved :: Apache Software License
Classifier: Programming Language :: Python
Classifier: Programming Language :: Python :: 3.8
Classifier: Programming Language :: Cython
Requires-Python: >=3.8
License-File: LICENSE
Requires-Dist: Cython>=0.29.14
Requires-Dist: numpy>=1.22.2
Requires-Dist: rasterio>=1.2.10
Requires-Dist: scipy>=1.8.0
Requires-Dist: scikit-image
Requires-Dist: PyYAML
Requires-Dist: tqdm
Requires-Dist: argcomplete
Requires-Dist: psutil
Requires-Dist: pylint
Provides-Extra: dev
Requires-Dist: pre-commit; extra == "dev"
Requires-Dist: build; extra == "dev"
Requires-Dist: isort>=5.8.0; extra == "dev"
Requires-Dist: black>=24.1a1; extra == "dev"
Requires-Dist: flake8>=3.9.1; extra == "dev"
Requires-Dist: flake8-comprehensions>=3.4.0; extra == "dev"
Requires-Dist: flake8-bugbear>=21.4.3; extra == "dev"
Requires-Dist: flake8-pyproject; extra == "dev"
Requires-Dist: pylint>=2.8.12; extra == "dev"
Requires-Dist: pytest; extra == "dev"
Requires-Dist: pytest-cov; extra == "dev"
Requires-Dist: pytest-sugar; extra == "dev"
Requires-Dist: mypy; extra == "dev"
Provides-Extra: docs
Requires-Dist: mkdocs; extra == "docs"
Provides-Extra: notebook
Requires-Dist: matplotlib; extra == "notebook"
Requires-Dist: jupyterlab; extra == "notebook"
Dynamic: license-file
